jreadability/__init__.py
jreadability/jreadability.py
jreadability-1.1.4.dist-info/licenses/LICENSE
jreadability-1.1.4.dist-info/METADATA
jreadability-1.1.4.dist-info/WHEEL
jreadability-1.1.4.dist-info/top_level.txt
jreadability-1.1.4.dist-info/RECORD
