Metadata-Version: 2.4
Name: jreadability
Version: 1.1.4
Summary: Calculate readability scores for Japanese texts.
Author-email: Joshua Hamilton <hamiltonjoshuadavid@gmail.com>
License: MIT License
Project-URL: homepage, https://github.com/joshdavham/jreadability
Keywords: japanese,readability
Classifier: Programming Language :: Python :: 3
Classifier: License :: OSI Approved :: MIT License
Classifier: Operating System :: OS Independent
Requires-Python: >=3.9
License-File: LICENSE
Requires-Dist: fugashi
Requires-Dist: unidic-lite
Provides-Extra: dev
Requires-Dist: setuptools; extra == "dev"
Requires-Dist: pytest; extra == "dev"
Requires-Dist: ruff; extra == "dev"
Dynamic: license-file
